redictum/__init__.py
redictum/dictum.py
redictum/pkg_meta.py
redictum/repo.py
redictum/store_base.py
redictum/tracer.py
redictum/store/__init__.py
redictum/store/rdbms.py
redictum-0.0.2.dist-info/LICENSE
redictum-0.0.2.dist-info/METADATA
redictum-0.0.2.dist-info/WHEEL
redictum-0.0.2.dist-info/entry_points.txt
redictum-0.0.2.dist-info/top_level.txt
redictum-0.0.2.dist-info/RECORD
