Metadata-Version: 2.1
Name: redictum
Version: 0.0.2
Summary: Dictum repository
Home-page: https://github.com/mwri/redictum
Author: Michael Wright
Author-email: mjw@methodanalysis.com
License: UNKNOWN
Platform: UNKNOWN
Classifier: Programming Language :: Python :: 3
Classifier: License :: OSI Approved :: MIT License
Classifier: Operating System :: OS Independent
Requires-Python: >=3.6
Requires-Dist: bencode.py (==4.0.0)
Requires-Dist: singleton-type (==0.0.4)
Requires-Dist: sqlalchemy (==1.4.37)
Provides-Extra: dev
Requires-Dist: black (==22.3.0) ; extra == 'dev'
Requires-Dist: coverage (==6.2) ; extra == 'dev'
Requires-Dist: freezegun (==1.2.1) ; extra == 'dev'
Requires-Dist: isort (==5.10.1) ; extra == 'dev'
Requires-Dist: pytest (==7.0.1) ; extra == 'dev'
